sp_bh_pcj_2020_2035/__init__.py
sp_bh_pcj_2020_2035/lyr.py
sp_bh_pcj_2020_2035/data/output/geo/barragens previstas - pontos.7z
sp_bh_pcj_2020_2035/data/output/geo/bioma - poligonos.7z
sp_bh_pcj_2020_2035/data/output/geo/caracterização vegetação ibge zonas - poligonos.7z
sp_bh_pcj_2020_2035/data/output/geo/domínio morfoestrutural - poligonos.7z
sp_bh_pcj_2020_2035/data/output/geo/geologia - poligonos.7z
sp_bh_pcj_2020_2035/data/output/geo/hidrografia principal - linhas.7z
sp_bh_pcj_2020_2035/data/output/geo/hidrografias secundárias - linhas.7z
sp_bh_pcj_2020_2035/data/output/geo/limite da bacia pcj - poligonos.7z
sp_bh_pcj_2020_2035/data/output/geo/limite de sub-bacias - poligonos.7z
sp_bh_pcj_2020_2035/data/output/geo/limite estadual - poligonos.7z
sp_bh_pcj_2020_2035/data/output/geo/municipal - poligonos.7z
sp_bh_pcj_2020_2035/data/output/geo/municipal de interesse regional - poligonos.7z
sp_bh_pcj_2020_2035/data/output/geo/nascentes - pontos.7z
sp_bh_pcj_2020_2035/data/output/geo/outorgas daee - pontos.7z
sp_bh_pcj_2020_2035/data/output/geo/pedologia - poligonos.7z
sp_bh_pcj_2020_2035/data/output/geo/priorização conservação recuperação restrição - poligonos.7z
sp_bh_pcj_2020_2035/data/output/geo/regional - poligonos.7z
sp_bh_pcj_2020_2035/data/output/geo/regional de grande porte - poligonos.7z
sp_bh_pcj_2020_2035/data/output/geo/região geomorfológica - poligonos.7z
sp_bh_pcj_2020_2035/data/output/geo/represas principais - poligonos.7z
sp_bh_pcj_2020_2035/data/output/geo/represas secundárias - poligonos.7z
sp_bh_pcj_2020_2035/data/output/geo/rio tietê - linhas.7z
sp_bh_pcj_2020_2035/data/output/geo/rm piracicaba - poligonos.7z
sp_bh_pcj_2020_2035/data/output/geo/suscetibilidade à erosão - poligonos.7z
sp_bh_pcj_2020_2035/data/output/geo/unidade geomorfológica - poligonos.7z
sp_bh_pcj_2020_2035/data/output/geo/área de recarga - poligonos.7z
sp_bh_pcj_2020_2035/data/output/geo/áreas de contribuição - poligonos.7z
sp_bh_pcj_2020_2035-0.0.7.dist-info/LICENSE
sp_bh_pcj_2020_2035-0.0.7.dist-info/METADATA
sp_bh_pcj_2020_2035-0.0.7.dist-info/WHEEL
sp_bh_pcj_2020_2035-0.0.7.dist-info/top_level.txt
sp_bh_pcj_2020_2035-0.0.7.dist-info/RECORD
