Metadata-Version: 2.1
Name: sp-bh-pcj-2020-2035
Version: 0.0.7
Summary: Dados Espaciais da Agência das Bacias PCJ, com informações apresentadas no Plano de Bacias 2020-2035
Home-page: https://github.com/open-geodata/sp_bh_pcj-2020-2035
Author: Michel Metran
Author-email: michelmetran@gmail.com
Keywords: python,dados espaciais,geoprocessamento
Classifier: Programming Language :: Python :: 3
Classifier: License :: OSI Approved :: MIT License
Classifier: Operating System :: OS Independent
Classifier: Natural Language :: Portuguese
Classifier: Intended Audience :: Developers
Requires-Python: >=3
License-File: LICENSE
